ks_session_manager/__init__.py
ks_session_manager/env.py
ks_session_manager/errors.py
ks_session_manager/types.py
ks_session_manager/clients/__init__.py
ks_session_manager/clients/adapters.py
ks_session_manager/clients/pylogram.py
ks_session_manager/clients/telethon.py
ks_session_manager/converter/__init__.py
ks_session_manager/converter/converter.py
ks_session_manager/managers/__init__.py
ks_session_manager/managers/base_manager.py
ks_session_manager/managers/pylogram_manager.py
ks_session_manager/managers/telethon_manager.py
ks_session_manager/revisors/__init__.py
ks_session_manager/revisors/telethon_revisor.py
ks_session_manager/utils/__init__.py
ks_session_manager/utils/fs.py
ks_session_manager/utils/json.py
ks_session_manager/utils/metadata_generator.py
ks_session_manager/utils/parsers.py
ks_session_manager/utils/phone.py
ks_session_manager/utils/smartproxy.py
ks_session_manager-0.11.0.dist-info/METADATA
ks_session_manager-0.11.0.dist-info/WHEEL
ks_session_manager-0.11.0.dist-info/top_level.txt
ks_session_manager-0.11.0.dist-info/RECORD
