Metadata-Version: 2.2
Name: ks_session_manager
Version: 0.11.0
Summary: KS session manager
Author: pylakey
Requires-Python: >=3.10
Requires-Dist: telethon<1.39,>=1.30
Requires-Dist: cryptg
Requires-Dist: pylogram<1,>=0.6.0
Requires-Dist: pydantic<3,>2
Requires-Dist: pydantic_settings<3,>2
Requires-Dist: pydash
Dynamic: author
Dynamic: description
Dynamic: description-content-type
Dynamic: requires-dist
Dynamic: requires-python
Dynamic: summary
